my_little_ansible/__init__.py
my_little_ansible/inventory_loader.py
my_little_ansible/mla.py
my_little_ansible/ssh_client.py
my_little_ansible/modules/__init__.py
my_little_ansible/modules/apt_module.py
my_little_ansible/modules/base_module.py
my_little_ansible/modules/command_module.py
my_little_ansible/modules/copy_module.py
my_little_ansible/modules/service_module.py
my_little_ansible/modules/sysctl_module.py
my_little_ansible/modules/template_module.py
my_little_ansible-1.0.2.dist-info/METADATA
my_little_ansible-1.0.2.dist-info/WHEEL
my_little_ansible-1.0.2.dist-info/entry_points.txt
my_little_ansible-1.0.2.dist-info/top_level.txt
my_little_ansible-1.0.2.dist-info/RECORD
