Metadata-Version: 2.1
Name: my_little_ansible
Version: 1.0.2
Summary: A mini Ansible-like tool for configuring remote hosts
Author: Ton Nom
Author-email: tonemail@example.com
Classifier: Programming Language :: Python :: 3
Classifier: License :: OSI Approved :: MIT License
Classifier: Operating System :: OS Independent
Requires-Python: >=3.6
Requires-Dist: paramiko
Requires-Dist: pyyaml
Requires-Dist: jinja2
